battlebit_api/BattleBitApiClient.py
battlebit_api/ServerBuilder.py
battlebit_api/__init__.py
battlebit_api/examples/getting_and_filtering_servers.py
battlebit_api/model/AntiCheatProvider.py
battlebit_api/model/GameMode.py
battlebit_api/model/Map.py
battlebit_api/model/MapSize.py
battlebit_api/model/Region.py
battlebit_api/model/Server.py
battlebit_api/model/ServerFilter.py
battlebit_api/model/ServerList.py
battlebit_api-0.0.2.dist-info/LICENSE
battlebit_api-0.0.2.dist-info/METADATA
battlebit_api-0.0.2.dist-info/WHEEL
battlebit_api-0.0.2.dist-info/top_level.txt
battlebit_api-0.0.2.dist-info/RECORD
