Metadata-Version: 2.1
Name: battlebit-api
Version: 0.0.2
Summary: An abstraction layer for the BattleBit Public API
Author-email: David Rodenkirchen <davidr.develop@gmail.com>
Project-URL: Homepage, https://git.jdrodenkirchen.de/drodenkirchen/battlebit-api
Project-URL: Bug Tracker, https://git.jdrodenkirchen.de/drodenkirchen
Classifier: Programming Language :: Python :: 3
Classifier: License :: Other/Proprietary License
Classifier: Operating System :: OS Independent
Classifier: Development Status :: 3 - Alpha
Classifier: Topic :: Games/Entertainment :: First Person Shooters
Classifier: Typing :: Typed
Requires-Python: >=3.7
License-File: LICENSE
Requires-Dist: requests ~=2.31.0
